simple_export/.idea/.gitignore
simple_export/.idea/inspectionProfiles/profiles_settings.xml
simple_export/.idea/inspectionProfiles/Project_Default.xml
simple_export/.idea/misc.xml
simple_export/.idea/modules.xml
simple_export/.idea/simple_export.iml
simple_export/.idea/vcs.xml
simple_export/__init__.py
simple_export/example.py
simple_export/excel.py
simple_export/template/excel1.xlsx
simple_export/template/excel2.xlsx
simple_export/template/excel3.xlsx
simple_export/template/excel4.xlsx
simple_export/template/excel5.xlsx
simple_export/template/excel6.xlsx
simple_export/utils/__init__.py
simple_export/utils/tool.py
simple_export/utils/util.py
simple_export/val1.xlsx
simple_export-0.3.6.dist-info/LICENSE
simple_export-0.3.6.dist-info/METADATA
simple_export-0.3.6.dist-info/WHEEL
simple_export-0.3.6.dist-info/RECORD
